boilerplate/__init__.py
boilerplate/trainer.py
boiler_plate_pytorch-0.0.1.dist-info/LICENSE
boiler_plate_pytorch-0.0.1.dist-info/METADATA
boiler_plate_pytorch-0.0.1.dist-info/WHEEL
boiler_plate_pytorch-0.0.1.dist-info/top_level.txt
boiler_plate_pytorch-0.0.1.dist-info/RECORD
